netbox_napalm_plugin/__init__.py
netbox_napalm_plugin/filtersets.py
netbox_napalm_plugin/forms.py
netbox_napalm_plugin/models.py
netbox_napalm_plugin/navigation.py
netbox_napalm_plugin/tables.py
netbox_napalm_plugin/urls.py
netbox_napalm_plugin/views.py
netbox_napalm_plugin/api/__init__.py
netbox_napalm_plugin/api/serializers.py
netbox_napalm_plugin/api/urls.py
netbox_napalm_plugin/api/views.py
netbox_napalm_plugin/migrations/0001_initial.py
netbox_napalm_plugin/migrations/0002_auto_20230215_1752.py
netbox_napalm_plugin/migrations/__init__.py
netbox_napalm_plugin/static/netbox_napalm_plugin/js/config.js
netbox_napalm_plugin/static/netbox_napalm_plugin/js/lldp.js
netbox_napalm_plugin/static/netbox_napalm_plugin/js/status.js
netbox_napalm_plugin/templates/netbox_napalm_plugin/config.html
netbox_napalm_plugin/templates/netbox_napalm_plugin/lldp_neighbors.html
netbox_napalm_plugin/templates/netbox_napalm_plugin/napalmplatformconfig.html
netbox_napalm_plugin/templates/netbox_napalm_plugin/status.html
nearoute_napalm_plugin-0.1.0.dist-info/LICENSE
nearoute_napalm_plugin-0.1.0.dist-info/METADATA
nearoute_napalm_plugin-0.1.0.dist-info/WHEEL
nearoute_napalm_plugin-0.1.0.dist-info/top_level.txt
nearoute_napalm_plugin-0.1.0.dist-info/RECORD
