Metadata-Version: 2.1
Name: nearoute-napalm-plugin
Version: 0.1.0
Summary: NetBox plugin for Napalm.
Author-email: Arthur Hanson <ahanson@netboxlabs.com>
Project-URL: Documentation, https://github.com/netbox-community/netbox-napalm-plugin/blob/main/README.md
Project-URL: Source, https://github.com/netbox-community/netbox-napalm-plugin
Project-URL: Tracker, https://github.com/netbox-community/netbox-napalm-plugin/issues
Classifier: Development Status :: 3 - Alpha
Classifier: Intended Audience :: Developers
Classifier: Natural Language :: English
Classifier: Programming Language :: Python :: 3 :: Only
Classifier: Programming Language :: Python :: 3.10
Classifier: Programming Language :: Python :: 3.11
Classifier: Programming Language :: Python :: 3.12
Requires-Python: >=3.10.0
License-File: LICENSE
Requires-Dist: napalm <5.0
Provides-Extra: test
Requires-Dist: black ==24.3.0 ; extra == 'test'
Requires-Dist: check-manifest ==0.49 ; extra == 'test'
Requires-Dist: flake8 ; extra == 'test'
Requires-Dist: flake8-pyproject ; extra == 'test'
Requires-Dist: pre-commit ==3.7.0 ; extra == 'test'
Requires-Dist: pytest ==8.1.1 ; extra == 'test'
